<?xml version="1.0" encoding="UTF-8"?><record_update>
    <sys_dictionary action="DELETE" element="bldg_room_numer" table="x_1534869_rrm_conference_room">
        <active>true</active>
        <array>false</array>
        <attributes/>
        <audit>false</audit>
        <calculation/>
        <choice>0</choice>
        <choice_field/>
        <choice_table/>
        <column_label>BLDG / Room Numer</column_label>
        <comments/>
        <create_roles/>
        <default_value/>
        <defaultsort/>
        <delete_roles/>
        <dependent/>
        <dependent_on_field/>
        <display>false</display>
        <dynamic_creation>false</dynamic_creation>
        <dynamic_creation_script/>
        <dynamic_default_value/>
        <dynamic_ref_qual/>
        <element>bldg_room_numer</element>
        <element_reference>false</element_reference>
        <foreign_database/>
        <formula/>
        <function_definition/>
        <function_field>false</function_field>
        <internal_type display_value="String">string</internal_type>
        <mandatory>true</mandatory>
        <max_length>40</max_length>
        <name>x_1534869_rrm_conference_room</name>
        <next_element/>
        <primary>false</primary>
        <read_only>false</read_only>
        <read_roles/>
        <reference/>
        <reference_cascade_rule/>
        <reference_floats>false</reference_floats>
        <reference_key/>
        <reference_qual/>
        <reference_qual_condition/>
        <reference_type/>
        <spell_check>false</spell_check>
        <staged>false</staged>
        <sys_class_name>sys_dictionary</sys_class_name>
        <sys_created_by>m.mackey</sys_created_by>
        <sys_created_on>2024-11-27 18:31:26</sys_created_on>
        <sys_id>4d31c4c7094212107f445f17a5103505</sys_id>
        <sys_name>BLDG / Room Numer</sys_name>
        <sys_package display_value="Room Reservation Manager" source="x_1534869_rrm">8cb0431e83021e102b825e65eeaad38a</sys_package>
        <sys_policy/>
        <sys_scope display_value="Room Reservation Manager">8cb0431e83021e102b825e65eeaad38a</sys_scope>
        <sys_update_name>sys_dictionary_x_1534869_rrm_conference_room_bldg_room_numer</sys_update_name>
        <sys_updated_by>m.mackey</sys_updated_by>
        <sys_updated_on>2024-11-27 18:31:28</sys_updated_on>
        <table_reference>false</table_reference>
        <text_index>false</text_index>
        <unique>false</unique>
        <use_dependent_field>false</use_dependent_field>
        <use_dynamic_default>false</use_dynamic_default>
        <use_reference_qualifier>simple</use_reference_qualifier>
        <virtual>false</virtual>
        <virtual_type>script</virtual_type>
        <widget/>
        <write_roles/>
        <xml_view>false</xml_view>
    </sys_dictionary>
    <sys_update_version action="INSERT_OR_UPDATE">
        <action>DELETE</action>
        <application display_value="Room Reservation Manager">8cb0431e83021e102b825e65eeaad38a</application>
        <file_path/>
        <instance_id>8b5fc4c5db0a1e50018f20c9139619f4</instance_id>
        <instance_name>adf-nov20-136-003</instance_name>
        <name>sys_dictionary_x_1534869_rrm_conference_room_bldg_room_numer</name>
        <payload><![CDATA[<?xml version="1.0" encoding="UTF-8"?><record_update><sys_dictionary action="INSERT_OR_UPDATE" element="bldg_room_numer" table="x_1534869_rrm_conference_room"><active>true</active><array>false</array><attributes/><audit>false</audit><calculation/><choice>0</choice><choice_field/><choice_table/><column_label>BLDG / Room Numer</column_label><comments/><create_roles/><default_value/><defaultsort/><delete_roles/><dependent/><dependent_on_field/><display>false</display><dynamic_creation>false</dynamic_creation><dynamic_creation_script/><dynamic_default_value/><dynamic_ref_qual/><element>bldg_room_numer</element><element_reference>false</element_reference><foreign_database/><formula/><function_definition/><function_field>false</function_field><internal_type display_value="String">string</internal_type><mandatory>true</mandatory><max_length>40</max_length><name>x_1534869_rrm_conference_room</name><next_element/><primary>false</primary><read_only>false</read_only><read_roles/><reference/><reference_cascade_rule/><reference_floats>false</reference_floats><reference_key/><reference_qual/><reference_qual_condition/><reference_type/><spell_check>false</spell_check><staged>false</staged><sys_class_name>sys_dictionary</sys_class_name><sys_created_by>m.mackey</sys_created_by><sys_created_on>2024-11-27 18:31:26</sys_created_on><sys_id>4d31c4c7094212107f445f17a5103505</sys_id><sys_name>BLDG / Room Numer</sys_name><sys_package display_value="Room Reservation Manager" source="x_1534869_rrm">8cb0431e83021e102b825e65eeaad38a</sys_package><sys_policy/><sys_scope display_value="Room Reservation Manager">8cb0431e83021e102b825e65eeaad38a</sys_scope><sys_update_name>sys_dictionary_x_1534869_rrm_conference_room_bldg_room_numer</sys_update_name><sys_updated_by>m.mackey</sys_updated_by><sys_updated_on>2024-11-27 18:31:28</sys_updated_on><table_reference>false</table_reference><text_index>false</text_index><unique>false</unique><use_dependent_field>false</use_dependent_field><use_dynamic_default>false</use_dynamic_default><use_reference_qualifier>simple</use_reference_qualifier><virtual>false</virtual><virtual_type>script</virtual_type><widget/><write_roles/><xml_view>false</xml_view></sys_dictionary></record_update>]]></payload>
        <payload_hash>144074165</payload_hash>
        <record_name>Conference Room.BLDG / Room Numer</record_name>
        <reverted_from/>
        <source>d03e4924d41612107f4489ee789dc8a9</source>
        <source_table>sys_update_set</source_table>
        <state>previous</state>
        <sys_created_by>m.mackey</sys_created_by>
        <sys_created_on>2024-12-02 15:58:49</sys_created_on>
        <sys_id>823e0d24d41612107f4489ee789dc833</sys_id>
        <sys_mod_count>0</sys_mod_count>
        <sys_recorded_at>1938818884d0000001</sys_recorded_at>
        <sys_updated_by>m.mackey</sys_updated_by>
        <sys_updated_on>2024-12-02 15:58:49</sys_updated_on>
        <type>Dictionary</type>
        <update_guid>a131c4c7ee4212101707f56d35feb784</update_guid>
        <update_guid_history>a131c4c7ee4212101707f56d35feb784:144074165,756909ace9d21210c439b8641fe13670:-1114002815,a131c4c7ee4212101707f56d35feb784:144074165,dd31c4c7054212102962b9110cf2391f:1325688095</update_guid_history>
    </sys_update_version>
    <sys_metadata_delete action="INSERT_OR_UPDATE">
        <sys_audit_delete/>
        <sys_class_name>sys_metadata_delete</sys_class_name>
        <sys_created_by>m.mackey</sys_created_by>
        <sys_created_on>2024-12-02 17:34:16</sys_created_on>
        <sys_db_object display_value="" name="sys_dictionary">sys_dictionary</sys_db_object>
        <sys_id>9a333790ead2431080f63159b4b81264</sys_id>
        <sys_metadata>4d31c4c7094212107f445f17a5103505</sys_metadata>
        <sys_mod_count>0</sys_mod_count>
        <sys_name>BLDG / Room Numer</sys_name>
        <sys_package display_value="Room Reservation Manager" source="x_1534869_rrm">8cb0431e83021e102b825e65eeaad38a</sys_package>
        <sys_parent display_value="">a0e9031a83421e102b825e65eeaad3a8</sys_parent>
        <sys_policy/>
        <sys_scope display_value="Room Reservation Manager">8cb0431e83021e102b825e65eeaad38a</sys_scope>
        <sys_scope_delete display_value="">1d2a0a09fed841648369685ce5209690</sys_scope_delete>
        <sys_update_name>sys_dictionary_x_1534869_rrm_conference_room_bldg_room_numer</sys_update_name>
        <sys_update_version display_value="sys_dictionary_x_1534869_rrm_conference_room_bldg_room_numer">823e0d24d41612107f4489ee789dc833</sys_update_version>
        <sys_updated_by>m.mackey</sys_updated_by>
        <sys_updated_on>2024-12-02 17:34:16</sys_updated_on>
    </sys_metadata_delete>
</record_update>
